nsholen/__init__.py
nsholen/main.py
nsholen/utils.py
nsholen-0.0.0.dev0.dist-info/METADATA
nsholen-0.0.0.dev0.dist-info/WHEEL
nsholen-0.0.0.dev0.dist-info/top_level.txt
nsholen-0.0.0.dev0.dist-info/RECORD
