Metadata-Version: 2.4
Name: nsholen
Version: 0.0.0.dev0
Summary: Labubu
Author-email: Orly Neto <orly2carvalhoneto@gmail.com>
Maintainer-email: Orly Neto <orly2carvalhoneto@gmail.com>
License-Expression: MIT
Keywords: NationStates
Requires-Python: >=3.10
Requires-Dist: requests==2.32.5
